{"id": "223", "type": "class", "data": "{\"code_str\": \"class Normalizer:\\n    def __init__(self, values=None, fixed_min_val=None, fixed_max_val=None):\\n        self.values = np.asarray(values) if values is not None else np.array()\\n        self.fixed_min_val = fixed_min_val\\n        self.fixed_max_val = fixed_max_val\\n        self.min_val = fixed_min_val or np.min(values)\\n        self.max_val = fixed_max_val or np.max(values)\\n        if self.min_val == self.max_val:\\n            self.result = np.array([0.5] * len(values))\\n        else:\\n            self.result = (self.values - self.min_val) / (self.max_val - self.min_val)\", \"name\": \"Normalizer\"}", "created_at": null, "updated_at": 1751906432.740633}